{
    "$schema": "http://json-schema.org/draft-04/schema#",
    "enum": [
        "CARD_TYPE_UNSPECIFIED",
        0,
        "MOVE_HORIZONTALLY",
        1,
        "PARANOIA_PLUS",
        2,
        "PARANOIA_MINUS",
        3,
        "GOODWILL_PLUS",
        4,
        "GOODWILL_MINUS",
        5,
        "INTRIGUE_PLUS",
        6,
        "FORBID_MOVEMENT",
        7,
        "FORBID_PARANOIA",
        8,
        "FORBID_GOODWILL",
        9,
        "FORBID_INTRIGUE",
        10,
        "MOVE_VERTICALLY",
        11,
        "MOVE_DIAGONALLY",
        12
    ],
    "oneOf": [
        {
            "type": "string"
        },
        {
            "type": "integer"
        }
    ],
    "title": "Card Type",
    "description": "卡牌类型"
}